LICENSE.txt
MANIFEST.in
README.md
setup.cfg
setup.py
requirements/requirements.txt
requirements/requirements_remote.txt
requirements/requirements_standalone.txt
vatis/live_asr/__init__.py
vatis/live_asr/config_variables.py
vatis/live_asr/logging.py
vatis/live_asr/config/__init__.py
vatis/live_asr/config/stream.py
vatis/live_asr/service/__init__.py
vatis/live_asr/service/auth.py
vatis/live_asr/stream/__init__.py
vatis/live_asr/stream/exception.py
vatis/live_asr/stream/factory.py
vatis/live_asr/stream/observer.py
vatis/live_asr/stream/transcription.py
vatis/live_asr/utils/__init__.py
vatis/live_asr/utils/generator.py
vatis/live_asr/utils/observer.py
vatis_asr_client.egg-info/PKG-INFO
vatis_asr_client.egg-info/SOURCES.txt
vatis_asr_client.egg-info/dependency_links.txt
vatis_asr_client.egg-info/namespace_packages.txt
vatis_asr_client.egg-info/not-zip-safe
vatis_asr_client.egg-info/requires.txt
vatis_asr_client.egg-info/top_level.txt