Metadata-Version: 2.1
Name: vatis-asr-client
Version: 1.2.0
Summary: Python implementation of the client for Vatis's ASR services
Home-page: https://gitlab.com/vatistech/asr-client-python
Maintainer: VATIS TECH
Maintainer-email: founders@vatis.tech
License: Apache Software License
Download-URL: https://gitlab.com/vatistech/asr-client-python/-/archive/1.2.0/asr-client-python-1.2.0.zip
Platform: Posix; MacOS X; Windows
Classifier: Development Status :: 4 - Beta
Classifier: Intended Audience :: Developers
Classifier: License :: OSI Approved :: Apache Software License
Classifier: Programming Language :: Python
Classifier: Programming Language :: Python :: 3
Classifier: Programming Language :: Python :: 3.6
Classifier: Programming Language :: Python :: 3.7
Classifier: Programming Language :: Python :: 3.8
Classifier: Operating System :: OS Independent
Classifier: Topic :: Software Development :: Build Tools
Classifier: Topic :: Internet
Requires-Python: >=3.6
Provides-Extra: remote
Provides-Extra: standalone
License-File: LICENSE.txt
